LICENSE.txt
MANIFEST.in
README.rst
setup.py
decision_optimization_client/__init__.py
decision_optimization_client/asset.py
decision_optimization_client/base_resource.py
decision_optimization_client/client.py
decision_optimization_client/container.py
decision_optimization_client/experiment.py
decision_optimization_client/proxyUtils.py
decision_optimization_client/solve.py
decision_optimization_client/table.py
decision_optimization_client/token.py
decision_optimization_client.egg-info/PKG-INFO
decision_optimization_client.egg-info/SOURCES.txt
decision_optimization_client.egg-info/dependency_links.txt
decision_optimization_client.egg-info/requires.txt
decision_optimization_client.egg-info/top_level.txt