Metadata-Version: 2.4
Name: decision_optimization_client
Version: 1.2.2
Summary: The IBM Decision Optimization Scenario Python client
Author: The IBM Decision Optimization on team
License: 
License-File: LICENSE.txt
Requires-Dist: requests
Requires-Dist: six
Dynamic: author
Dynamic: license
Dynamic: license-file
Dynamic: requires-dist
Dynamic: summary
